py_agent/__init__.py
py_agent/core.py
py_agent/interpreter.py
py_agent/llm.py
py_agent/prompts.py
py_agent/utils.py
llm_py_agent-0.1.0.dist-info/LICENSE
llm_py_agent-0.1.0.dist-info/METADATA
llm_py_agent-0.1.0.dist-info/WHEEL
llm_py_agent-0.1.0.dist-info/RECORD
