Metadata-Version: 2.1
Name: llm-py-agent
Version: 0.1.0
Summary: A Python agent framework that enables function-calling through LLM code generation
Home-page: https://github.com/acodercat/PyAgent
License: MIT
Keywords: llm,agent,code-generation,function-calling
Author: Ram
Author-email: codercat@163.com
Requires-Python: >=3.10,<3.13
Classifier: Development Status :: 4 - Beta
Classifier: Intended Audience :: Developers
Classifier: License :: OSI Approved :: MIT License
Classifier: Programming Language :: Python :: 3
Classifier: Programming Language :: Python :: 3.10
Classifier: Programming Language :: Python :: 3.11
Classifier: Programming Language :: Python :: 3.12
Classifier: Topic :: Software Development :: Libraries :: Python Modules
Requires-Dist: ipython (>=8.31.0,<9.0.0)
Requires-Dist: openai (>=1.59.3,<2.0.0)
Requires-Dist: rich (>=13.9.4,<14.0.0)
Project-URL: Documentation, https://github.com/acodercat/PyAgent#readme
Project-URL: Repository, https://github.com/acodercat/PyAgent
